apis/__init__.py
apis/api.py
apis/livecoin/__init__.py
apis/livecoin/api.py
settings/__init__.py
settings/config.py
utils/__init__.py
utils/decorators.py
trade_common-0.29.0.dist-info/METADATA
trade_common-0.29.0.dist-info/WHEEL
trade_common-0.29.0.dist-info/top_level.txt
trade_common-0.29.0.dist-info/RECORD
