Metadata-Version: 2.1
Name: trade-common
Version: 0.29.0
Summary: A common package with APIs and Utils
Home-page: https://github.com/amdrey-maralin/trade
Author: Andrey Maralin
Author-email: a.a.maralin@gmail.com
License: UNKNOWN
Platform: UNKNOWN
Classifier: Programming Language :: Python :: 3
Classifier: License :: OSI Approved :: MIT License
Classifier: Operating System :: OS Independent
Requires-Python: >=3.6
